<Properties StartupConfiguration="{A33DA48D-269C-412C-87C2-E9128AC22F82}|Default">
  <MonoDevelop.Ide.Workbench ActiveDocument="EsercizioSwitch/Program.cs">
    <Files>
      <File FileName="EsercizioSwitch/Program.cs" Line="9" Column="17" />
    </Files>
    <Pads>
      <Pad Id="ProjectPad">
        <State name="__root__">
          <Node name="EsercizioSwitch" expanded="True">
            <Node name="EsercizioSwitch" expanded="True">
              <Node name="Program.cs" selected="True" />
            </Node>
          </Node>
        </State>
      </Pad>
    </Pads>
  </MonoDevelop.Ide.Workbench>
  <MonoDevelop.Ide.DebuggingService.PinnedWatches />
  <MonoDevelop.Ide.Workspace ActiveConfiguration="Debug" />
  <MonoDevelop.Ide.ItemProperties.EsercizioSwitch FirstBuild="True" PreferredExecutionTarget="MonoDevelop.Default" />
  <MonoDevelop.Ide.DebuggingService.Breakpoints>
    <BreakpointStore />
  </MonoDevelop.Ide.DebuggingService.Breakpoints>
  <MultiItemStartupConfigurations />
</Properties>